yta_editor_nodes_gpu/__init__.py
yta_editor_nodes_gpu/blender/__init__.py
yta_editor_nodes_gpu/blender/abstract.py
yta_editor_nodes_gpu/blender/add.py
yta_editor_nodes_gpu/blender/alpha.py
yta_editor_nodes_gpu/blender/mix.py
yta_editor_nodes_gpu/blender/utils.py
yta_editor_nodes_gpu/complex/__init__.py
yta_editor_nodes_gpu/complex/abstract.py
yta_editor_nodes_gpu/complex/display_over_at.py
yta_editor_nodes_gpu/compositor/__init__.py
yta_editor_nodes_gpu/compositor/abstract.py
yta_editor_nodes_gpu/compositor/displacement_with_rotation.py
yta_editor_nodes_gpu/processor/__init__.py
yta_editor_nodes_gpu/processor/abstract.py
yta_editor_nodes_gpu/processor/black_and_white.py
yta_editor_nodes_gpu/processor/brightness.py
yta_editor_nodes_gpu/processor/color_contrast.py
yta_editor_nodes_gpu/processor/selection_mask.py
yta_editor_nodes_gpu/processor/video/__init__.py
yta_editor_nodes_gpu/processor/video/abstract.py
yta_editor_nodes_gpu/processor/video/breathing_frame.py
yta_editor_nodes_gpu/processor/video/experimental.py
yta_editor_nodes_gpu/processor/video/trajectory.py
yta_editor_nodes_gpu/processor/video/transitions/__init__.py
yta_editor_nodes_gpu/processor/video/transitions/abstract.py
yta_editor_nodes_gpu/processor/video/transitions/alphapedia_mask.py
yta_editor_nodes_gpu/processor/video/transitions/bars_falling.py
yta_editor_nodes_gpu/processor/video/transitions/circle_closing.py
yta_editor_nodes_gpu/processor/video/transitions/circle_opening.py
yta_editor_nodes_gpu/processor/video/transitions/crossfade.py
yta_editor_nodes_gpu/processor/video/transitions/distorted_crossfade.py
yta_editor_nodes_gpu/processor/video/transitions/slide.py
yta_editor_nodes_gpu/processor/video/waving_frame.py
yta_editor_nodes_gpu-0.1.5.dist-info/licenses/LICENSE
yta_editor_nodes_gpu-0.1.5.dist-info/METADATA
yta_editor_nodes_gpu-0.1.5.dist-info/WHEEL
yta_editor_nodes_gpu-0.1.5.dist-info/RECORD
