Metadata-Version: 2.4
Name: yta-editor-nodes-gpu
Version: 0.1.5
Summary: Youtube Autonomous Main Editor Nodes GPU module
License-File: LICENSE
Author: danialcala94
Author-email: danielalcalavalera@gmail.com
Requires-Python: ==3.9
Classifier: Programming Language :: Python :: 3
Classifier: Programming Language :: Python :: 3.9
Requires-Dist: moderngl (>=0.0.1,<9.0.0)
Requires-Dist: yta_validation (>=0.0.1,<1.0.0)
Requires-Dist: yta_video_opengl (>=0.0.1,<1.0.0)
